simpletweetlib/__init__.py
simpletweetlib/_auth.py
simpletweetlib/auth.py
simpletweetlib/profile.py
simpletweetlib/tweet.py
simpletweetlib-0.0.1.dist-info/LICENSE
simpletweetlib-0.0.1.dist-info/METADATA
simpletweetlib-0.0.1.dist-info/WHEEL
simpletweetlib-0.0.1.dist-info/top_level.txt
simpletweetlib-0.0.1.dist-info/RECORD
