Metadata-Version: 2.1
Name: simpletweetlib
Version: 0.0.1
Summary: A quite simple and easy to use tweet library
Home-page: https://github.com/Miyoshi-Ryota/simpletweetlib
Author: Ryota Miyoshi
Author-email: m1yosh1.ry0t4@gmail.com
License: UNKNOWN
Platform: UNKNOWN
Classifier: Programming Language :: Python :: 3
Classifier: License :: OSI Approved :: MIT License
Classifier: Operating System :: OS Independent
Requires-Python: >=3.7
Requires-Dist: requests-oauthlib
